.DS_Store
EtherPy-0.0.700.dist-info/DESCRIPTION.rst
EtherPy-0.0.700.dist-info/METADATA
EtherPy-0.0.700.dist-info/RECORD
EtherPy-0.0.700.dist-info/WHEEL
EtherPy-0.0.700.dist-info/metadata.json
EtherPy-0.0.700.dist-info/top_level.txt
etherpy/Client.py
etherpy/Helper.py
etherpy/PersonalClient.py
etherpy/UnitMap.py
etherpy/__init__.py
