Metadata-Version: 2.0
Name: EtherPy
Version: 0.0.700
Summary: Python Ethereum Node Client
Home-page: https://pypi.python.org/pypi/EtherPy
Author: Chip Wasson
Author-email: chip@wasson.io
License: UNKNOWN
Platform: UNKNOWN
